drf_complex_filter/__init__.py
drf_complex_filter/comparisons.py
drf_complex_filter/filters.py
drf_complex_filter/functions.py
drf_complex_filter/settings.py
drf_complex_filter/utils.py
drf_complex_filter-2.0.2.dist-info/LICENSE
drf_complex_filter-2.0.2.dist-info/METADATA
drf_complex_filter-2.0.2.dist-info/WHEEL
drf_complex_filter-2.0.2.dist-info/top_level.txt
drf_complex_filter-2.0.2.dist-info/RECORD
