Metadata-Version: 2.2
Name: drf-complex-filter
Version: 2.0.2
Summary: Declarative filter for Django ORM
Author-email: Nikita Balobanov <kit-oz@ya.ru>
License: MIT License
Project-URL: Homepage, https://github.com/kit-oz/drf-complex-filter
Keywords: django,django-rest-framework,django-orm
Classifier: Development Status :: 4 - Beta
Classifier: Framework :: Django
Classifier: Intended Audience :: Developers
Classifier: License :: OSI Approved :: MIT License
Classifier: Operating System :: OS Independent
Classifier: Programming Language :: Python
Classifier: Programming Language :: Python :: 3
Requires-Python: >=3.6
License-File: LICENSE
Requires-Dist: django>=3.0.0
Provides-Extra: dev
Requires-Dist: djangorestframework~=3.12; extra == "dev"
Requires-Dist: parameterized~=0.7; extra == "dev"
Requires-Dist: mixer~=7.2.2; extra == "dev"
